python_hiccup/__init__.py
python_hiccup/py.typed
python_hiccup/html/__init__.py
python_hiccup/html/core.py
python_hiccup/transform/__init__.py
python_hiccup/transform/core.py
python_hiccup-0.4.0.dist-info/METADATA
python_hiccup-0.4.0.dist-info/WHEEL
python_hiccup-0.4.0.dist-info/licenses/LICENSE
python_hiccup-0.4.0.dist-info/RECORD
