Metadata-Version: 2.4
Name: python-hiccup
Version: 0.4.0
Summary: Python Hiccup is a library for representing HTML using plain Python data structures
Project-URL: Repository, https://github.com/DavidVujic/python-hiccup
Author: David Vujic
License-File: LICENSE
Requires-Python: >=3.10
